LICENSE
MANIFEST.in
README.rst
setup.py
simplespectral.py
SimpleSpectral.egg-info/PKG-INFO
SimpleSpectral.egg-info/SOURCES.txt
SimpleSpectral.egg-info/dependency_links.txt
SimpleSpectral.egg-info/requires.txt
SimpleSpectral.egg-info/top_level.txt