Metadata-Version: 1.1
Name: SimpleSpectral
Version: 1.0.0
Summary: Heavily simplified scipy.signal.spectral module which only depends on NumPy and supports pyFFTW
Home-page: https://github.com/xmikos/simplespectral
Author: Michal Krenek (Mikos)
Author-email: m.krenek@gmail.com
License: MIT
Platform: UNKNOWN
Classifier: Development Status :: 4 - Beta
Classifier: Intended Audience :: Developers
Classifier: Intended Audience :: Science/Research
Classifier: License :: OSI Approved :: MIT License
Classifier: Natural Language :: English
Classifier: Operating System :: OS Independent
Classifier: Programming Language :: Python :: 3
Classifier: Topic :: Software Development :: Libraries :: Python Modules
Classifier: Topic :: Scientific/Engineering
